zcross/__init__.py
zcross/binding.py
zcross/zcross_plot.py
zcross/zcross_xml.py
zcross/raw/__init__.py
zcross/raw/binding.py
zcross-0.0.15.dist-info/LICENSE
zcross-0.0.15.dist-info/METADATA
zcross-0.0.15.dist-info/WHEEL
zcross-0.0.15.dist-info/entry_points.txt
zcross-0.0.15.dist-info/top_level.txt
zcross-0.0.15.dist-info/RECORD
