Metadata-Version: 2.1
Name: zcross
Version: 0.0.15
Summary: An utility to read low-pressure gaseous cross sections data
Home-page: https://gitlab.com/micrenda/zcross-python
Author: Michele Renda
Author-email: michele.renda@cern.ch
License: UNKNOWN
Platform: UNKNOWN
Classifier: Programming Language :: Python :: 3
Classifier: License :: OSI Approved :: GNU Lesser General Public License v3 or later (LGPLv3+)
Classifier: Operating System :: OS Independent
Requires-Python: >=3.0
Requires-Dist: matplotlib
Requires-Dist: pint
Requires-Dist: pyxb
